{
  "project_info": {
    "project_number": "328829441572",
    "project_id": "om-satya-exim-pvt-ltd",
    "storage_bucket": "om-satya-exim-pvt-ltd.firebasestorage.app"
  },
  "client": [
    {
      "client_info": {
        "mobilesdk_app_id": "1:328829441572:android:4f4a8d6e2957251b182ab1",
        "android_client_info": {
          "package_name": "com.oms.eximpvtltd"
        }
      },
      "oauth_client": [],
      "api_key": [
        {
          "current_key": "AIzaSyDz1sjgaGFk6Dw8ETyrHrM1y1N6T1JAo-0"
        }
      ],
      "services": {
        "appinvite_service": {
          "other_platform_oauth_client": []
        }
      }
    }
  ],
  "configuration_version": "1"
}